{
  "m_GameObject": {
    "m_FileID": 0,
    "m_PathID": 5558989032022829025
  },
  "m_Enabled": 1,
  "m_Script": {
    "m_FileID": 0,
    "m_PathID": -6346430600214344638
  },
  "m_Name": "",
  "Ladder": "",
  "PlayFabId": "",
  "Rank": 0,
  "Frame": {
    "m_FileID": 0,
    "m_PathID": 8457686647594396790
  },
  "No": {
    "m_FileID": 0,
    "m_PathID": 1487338730175991871
  },
  "Username": {
    "m_FileID": 0,
    "m_PathID": 393982994366698317
  },
  "Score": {
    "m_FileID": 0,
    "m_PathID": 5454127452401778482
  },
  "Replay": {
    "m_FileID": 0,
    "m_PathID": 3997162574495747430
  }
}